
[
    {
        "id": 1,
        "image": "/src/assets/projects/obra01.jpg",
        "residencial": " Edificio Torre Sipan",
        "name": "Inversiones Beraca S.A.C.",
        "address": "Miraflores",
        "numdpto": "20",
        "year": "Mayo 2012",
        "g_maps": "C. Chiclayo 170, Lima 15074, Peru"
    },
    {
        "id": 2,
        "image": "/src/assets/projects/obra02.jpg",
        "residencial": "Mirador de la Reserva",
        "name": "Inmobiliaria Beraca & Bostad S.A.C.",
        "address": "Lince",
        "numdpto": "50",
        "year": "Octubre 2015",
        "g_maps": "Manuel Castañeda 237, Lima 15046"
    },
    {
        "id": 3,
        "image": "/src/assets/projects/obra03.jpg",
        "residencial": " Bambamarca",
        "name": "Personal Natural",
        "address": "Cajamarca",
        "numdpto": "21",
        "year": "Enero 2018",
        "g_maps": "Jirón Arequipa 253, Lima 15086"
    },
    {
        "id": 4,
        "image": "/src/assets/projects/obra04.jpg",
        "residencial": " Edificio Verástegui  ",
        "name": "GHS CONSTRUCTORA S.A.C.",
        "address": "San Jua de Miraflores",
        "numdpto": "26",
        "year": "Noviembre 2020",
        "g_maps": "C. Ignacio Seminario 903, Lima 15824, Peru"
    },
    {
        "id": 5,
        "image": "/src/assets/projects/obra05.jpg",
        "residencial": " Puente Verde",
        "name": "Grupo DyM Constructora S.A.C.",
        "address": "Ate  ",
        "numdpto": "18",
        "year": "Junio 2019",
        "g_maps": "Av. el Banco N° 214, Ate 15026"
    },
    {
        "id": 6,
        "image": "/src/assets/projects/obra06.jpg",
        "residencial": " El Prado",
        "name": "Grupo DyM Constructora S.A.C.",
        "address": "Ate  ",
        "numdpto": "24",
        "year": "Febrero 2020",
        "g_maps": "Av. Javier Prado Este 7845, Ate 15012"
    },
    {
        "id": 7,
        "image": "/src/assets/projects/obra07.jpg",
        "residencial": "Monterrico Alto",
        "name": "Grupo DyM Constructora S.A.C.",
        "address": "Salamanca",
        "numdpto": "24",
        "year": "Junio 2021 ",
        "g_maps": "Calle 3, Mz. D,  de Monterrico, Ate 15022"
    },
    {
        "id": 8,
        "image": "/src/assets/projects/obra08.jpg",
        "residencial": "Parque Prada",
        "name": "GHS CONSTRUCTORA S.A.C.",
        "address": "Magdalena",
        "numdpto": "12",
        "year": "Agosto de 2021",
        "g_maps": "Av. Parque Gonzales Prada 667, Magdalena del Mar 15076"
    },
    {
        "id": 9,
        "image": "/src/assets/projects/obra09.jpg",
        "residencial": "Ventura",
        "name": "Urbanica Proyectos Inmobiliarios S.A.C.",
        "address": "San Miguel",
        "numdpto": "14",
        "year": "Febrero 2022",
        "g_maps": "WVCX+9P3, San Miguel 15087"
    },
    {
        "id": 10,
        "image": "/src/assets/projects/obra10.jpg",
        "residencial": "Maddy",
        "name": "CONSTRUCTORA E INMOBILIARIA ICASA S.A.C",
        "address": "Magdalena del mar",
        "numdpto": "62",
        "year": "Mayo 2022 ",
        "g_maps": "Jr. Tacna 1056, Magdalena del Mar 15086"
    },
    {
        "id": 11,
        "image": "/src/assets/projects/obra11.jpg",
        "residencial": "Vidamor",
        "name": "Grupo DyM Constructora S.A.C.",
        "address": "ATE",
        "numdpto": "60",
        "year": "Diciembre 2022 ",
        "g_maps": "Av. Javier Prado Este 8111, Ate 15012"
    },
    {
        "id": 12,
        "image": "/src/assets/projects/obra12.jpg",
        "residencial": "Elenor",
        "name": "P&D Holding Group S.A.C.",
        "address": "Magdalena del mar",
        "numdpto": "32",
        "year": "Junio 2023 ",
        "g_maps": "Jirón Arequipa 253, Lima 15086"
    },
    {
        "id": 13,
        "image": "/src/assets/projects/obra13.jpg",
        "residencial": "Vittorie",
        "name": "GRUPO DYM CONSTRUCTORA S.A.C.",
        "address": "SURQUILLO",
        "numdpto": "57",
        "year": "Diciembre 2024 ",
        "g_maps": "Avenida Principal 915, Lima 15038, Peru"
    },
    {
        "id": 14,
        "image": "/src/assets/projects/obra14.jpg",
        "residencial": "Palmer ",
        "name": "GRUPO DYM CONSTRUCTORA S.A.C.",
        "address": "Breña",
        "numdpto": "102",
        "year": "Junio 2025 ",
        "g_maps": "Jr. Jorge Chávez 1039, Breña 15083, Peru"
    }
]
